rastervision/pytorch_learner/__init__.py
rastervision/pytorch_learner/classification_learner.py
rastervision/pytorch_learner/classification_learner_config.py
rastervision/pytorch_learner/learner.py
rastervision/pytorch_learner/learner_config.py
rastervision/pytorch_learner/object_detection_learner.py
rastervision/pytorch_learner/object_detection_learner_config.py
rastervision/pytorch_learner/object_detection_utils.py
rastervision/pytorch_learner/py.typed
rastervision/pytorch_learner/regression_learner.py
rastervision/pytorch_learner/regression_learner_config.py
rastervision/pytorch_learner/semantic_segmentation_learner.py
rastervision/pytorch_learner/semantic_segmentation_learner_config.py
rastervision/pytorch_learner/dataset/__init__.py
rastervision/pytorch_learner/dataset/classification_dataset.py
rastervision/pytorch_learner/dataset/dataset.py
rastervision/pytorch_learner/dataset/object_detection_dataset.py
rastervision/pytorch_learner/dataset/regression_dataset.py
rastervision/pytorch_learner/dataset/semantic_segmentation_dataset.py
rastervision/pytorch_learner/dataset/transform.py
rastervision/pytorch_learner/dataset/utils/__init__.py
rastervision/pytorch_learner/dataset/utils/utils.py
rastervision/pytorch_learner/dataset/visualizer/__init__.py
rastervision/pytorch_learner/dataset/visualizer/classification_visualizer.py
rastervision/pytorch_learner/dataset/visualizer/object_detection_visualizer.py
rastervision/pytorch_learner/dataset/visualizer/regression_visualizer.py
rastervision/pytorch_learner/dataset/visualizer/semantic_segmentation_visualizer.py
rastervision/pytorch_learner/dataset/visualizer/visualizer.py
rastervision/pytorch_learner/utils/__init__.py
rastervision/pytorch_learner/utils/distributed.py
rastervision/pytorch_learner/utils/prediction.py
rastervision/pytorch_learner/utils/torch_hub.py
rastervision/pytorch_learner/utils/utils.py
rastervision_pytorch_learner-0.31.1.dist-info/METADATA
rastervision_pytorch_learner-0.31.1.dist-info/WHEEL
rastervision_pytorch_learner-0.31.1.dist-info/top_level.txt
rastervision_pytorch_learner-0.31.1.dist-info/RECORD
