Metadata-Version: 2.1
Name: rastervision_pytorch_learner
Version: 0.31.1
Summary: A rastervision plugin that adds PyTorch training pipelines
Home-page: https://github.com/azavea/raster-vision
Author: Azavea
Author-email: info@azavea.com
License: Apache License 2.0
Keywords: raster deep-learning ml computer-vision earth-observation geospatial geospatial-processing
Classifier: Intended Audience :: Developers
Classifier: License :: OSI Approved :: Apache Software License
Classifier: Programming Language :: Python
Classifier: Programming Language :: Python :: 3
Requires-Dist: rastervision-pipeline
Requires-Dist: rastervision-core
Requires-Dist: numpy
Requires-Dist: pillow
Requires-Dist: torch
Requires-Dist: torchvision
Requires-Dist: tensorboard
Requires-Dist: albumentations
Requires-Dist: cython
Requires-Dist: pycocotools
Requires-Dist: psutil
Requires-Dist: opencv-python-headless
Requires-Dist: matplotlib
Requires-Dist: tqdm
Requires-Dist: onnx
